remla23team09librelease/VersionUtil.py
remla23team09librelease/__init__.py
remla23team09librelease-1.0.0.dist-info/METADATA
remla23team09librelease-1.0.0.dist-info/WHEEL
remla23team09librelease-1.0.0.dist-info/top_level.txt
remla23team09librelease-1.0.0.dist-info/RECORD
